godot_rl/__init__.py
godot_rl/main.py
godot_rl/core/__init__.py
godot_rl/core/godot_env.py
godot_rl/core/utils.py
godot_rl/download_utils/__init__.py
godot_rl/download_utils/download_examples.py
godot_rl/download_utils/download_godot_editor.py
godot_rl/download_utils/from_hub.py
godot_rl/wrappers/__init__.py
godot_rl/wrappers/clean_rl_wrapper.py
godot_rl/wrappers/petting_zoo_wrapper.py
godot_rl/wrappers/ray_wrapper.py
godot_rl/wrappers/sample_factory_wrapper.py
godot_rl/wrappers/sbg_single_obs_wrapper.py
godot_rl/wrappers/stable_baselines_wrapper.py
godot_rl/wrappers/onnx/__init__.py
godot_rl/wrappers/onnx/stable_baselines_export.py
godot_rl-0.8.2.dist-info/LICENSE
godot_rl-0.8.2.dist-info/METADATA
godot_rl-0.8.2.dist-info/WHEEL
godot_rl-0.8.2.dist-info/entry_points.txt
godot_rl-0.8.2.dist-info/top_level.txt
godot_rl-0.8.2.dist-info/RECORD
