Metadata-Version: 2.2
Name: godot_rl
Version: 0.8.2
Summary: A Deep Reinforcement Learning package for the Godot game engine
Author: Edward Beeching
Author-email: Edward Beeching <edbeeching@gmail.com>
License: MIT
Project-URL: Homepage, https://github.com/pypa/godot_rl_agents
Project-URL: Bug Tracker, https://github.com/pypa/godot_rl_agents/issues
Platform: unix
Platform: linux
Platform: osx
Platform: cygwin
Platform: win32
Classifier: Intended Audience :: Developers
Classifier: Intended Audience :: Education
Classifier: Intended Audience :: Science/Research
Classifier: Programming Language :: Python :: 3
Classifier: Programming Language :: Python :: 3.8
Classifier: Programming Language :: Python :: 3.9
Classifier: Programming Language :: Python :: 3.10
Classifier: Topic :: Scientific/Engineering :: Artificial Intelligence
Requires-Python: >=3.7
License-File: LICENSE
Requires-Dist: numpy
Requires-Dist: tensorboard
Requires-Dist: wget
Requires-Dist: huggingface_hub>=0.10
Requires-Dist: gymnasium<=1.0.0
Requires-Dist: stable-baselines3<=2.4.0,>=2.0.0
Requires-Dist: huggingface_sb3
Requires-Dist: onnx
Requires-Dist: onnxruntime
Provides-Extra: test
Requires-Dist: pytest>=6.0; extra == "test"
Requires-Dist: pytest-xdist; extra == "test"
Provides-Extra: dev
Requires-Dist: pytest>=6.0; extra == "dev"
Requires-Dist: pytest-xdist; extra == "dev"
Requires-Dist: black; extra == "dev"
Requires-Dist: flake8; extra == "dev"
Requires-Dist: isort; extra == "dev"
Requires-Dist: pyyaml>=5.3.1; extra == "dev"
Provides-Extra: sf
Requires-Dist: sample-factory; extra == "sf"
Provides-Extra: rllib
Requires-Dist: ray[rllib]; extra == "rllib"
Provides-Extra: cleanrl
Requires-Dist: wandb; extra == "cleanrl"
